setup.py
solevaluator/__init__.py
solevaluator/calc_durs.py
solevaluator/calc_pis.py
solevaluator/eval_solutil.py
solevaluator.egg-info/PKG-INFO
solevaluator.egg-info/SOURCES.txt
solevaluator.egg-info/dependency_links.txt
solevaluator.egg-info/not-zip-safe
solevaluator.egg-info/top_level.txt