Metadata-Version: 1.0
Name: solevaluator
Version: 0.1
Summary: Solution evaluator for the Benchmark Set of the ORSP (by Leeftink and Hans 2016).
Home-page: UNKNOWN
Author: Panagiotis Giannakoulias
Author-email: panosgia87@hotmail.com
License: Freeware
Platform: UNKNOWN
